dynaphos/__init__.py
dynaphos/cortex_models.py
dynaphos/image_processing.py
dynaphos/plotting.py
dynaphos/simulator.py
dynaphos/utils.py
dynaphos-0.1.3.dist-info/LICENSE
dynaphos-0.1.3.dist-info/METADATA
dynaphos-0.1.3.dist-info/WHEEL
dynaphos-0.1.3.dist-info/top_level.txt
dynaphos-0.1.3.dist-info/RECORD
