Metadata-Version: 2.1
Name: dynaphos
Version: 0.1.3
Summary: Fully differentiable and biologically plausible simulation of prosthetic vision.
Author-email: Maureen van der Grinten <maureen.vandergrinten@ru.nl>, Jaap de Ruyter <jaap.deruyter@donders.ru.nl>, Bodo Rueckauer <bodo.rueckauer@donders.ru.nl>
Project-URL: Homepage, https://github.com/neuralcodinglab/dynaphos.git
Classifier: Programming Language :: Python :: 3
Classifier: License :: OSI Approved :: GNU General Public License v3 (GPLv3)
Classifier: Operating System :: OS Independent
Requires-Python: >=3.7
License-File: LICENSE
